{
  "$schema": "https://schemas.wp.org/trunk/block.json",
  "apiVersion": 3,
  "name": "chsa/catalogit-model-viewer",
  "version": "0.1.0",
  "title": "CHSA CatalogIt Model Viewer",
  "category": "widgets",
  "description": "Displays a 3D model stored in an entry in CatalogIt.",
  "example": {},
  "attributes": {
    "entryId": {
      "type": "string"
    },
    "alt": {
      "type": "string"
    },
    "src": {
      "type": "string"
    }
  },
  "supports": {
    "align": [
      "wide"
    ],
    "html": false
  },
  "textdomain": "chsa-catalogit-model-viewer",
  "editorScript": "file:./index.js",
  "editorStyle": "file:./index.css",
  "style": "file:./style-index.css",
  "viewScript": "file:./view.js"
}